LICENSE.md
MANIFEST.in
README.md
setup.cfg
setup.py
ii_drf_testtools/__init__.py
ii_drf_testtools/mixins.py
ii_drf_testtools/settings.py
ii_drf_testtools/utils.py
ii_drf_testtools.egg-info/PKG-INFO
ii_drf_testtools.egg-info/SOURCES.txt
ii_drf_testtools.egg-info/dependency_links.txt
ii_drf_testtools.egg-info/not-zip-safe
ii_drf_testtools.egg-info/requires.txt
ii_drf_testtools.egg-info/top_level.txt