Metadata-Version: 1.1
Name: ii-drf-testtools
Version: 0.2
Summary: ideallical django-restframework testtools
Home-page: https://github.com/ideallical/ii_drf_testtools
Author: ideallical
Author-email: info@ideallical.com
License: BSD
Download-URL: https://github.com/ideallical/ii_drf_testtools/archive/0.2.tar.gz
Keywords: testing,drf
Platform: UNKNOWN
